PyEcoLib/PopSimulator.py
PyEcoLib/simulator.py
PyEcoLib/models/__init__.py
PyEcoLib/models/cell.py
PyEcoLib-2.0.3.dist-info/LICENSE
PyEcoLib-2.0.3.dist-info/METADATA
PyEcoLib-2.0.3.dist-info/WHEEL
PyEcoLib-2.0.3.dist-info/top_level.txt
PyEcoLib-2.0.3.dist-info/RECORD
