Metadata-Version: 2.1
Name: PyEcoLib
Version: 2.0.3
Summary: PyEcoLib (Python Library for E. coli size dynamics estimation) is library to estimate bacterial cell size stochastic dynamics including time-continuous growth process and division events.
Home-page: https://github.com/SystemsBiologyUniandes/PyEcoLib
Author: Cesar Vargas, César Nieto, Camilo Blanco
Author-email: cavargar@gmail.com, canietoa@gmail.com, sergio.camilo.blanco@gmail.com
License: UNKNOWN
Platform: UNKNOWN
Classifier: Programming Language :: Python :: 3
Classifier: License :: OSI Approved :: MIT License
Requires-Python: >=3.6
